README
setup.cfg
setup.py
bin/exgrexCourseraPy
exgrex/__init__.py
exgrex/decorators.py
exgrex/graders.py
exgrex/result.py
exgrex_py.egg-info/PKG-INFO
exgrex_py.egg-info/SOURCES.txt
exgrex_py.egg-info/dependency_links.txt
exgrex_py.egg-info/top_level.txt
test/__init__.py
test/test_graders.py