Metadata-Version: 2.1
Name: exgrex-py
Version: 0.3a2
Summary: Exgrex implementation for the Python programming language.
Home-page: https://github.com/vshagur/exgrex-py
Author: vshagur
Author-email: vshagur@gmail.com
License: UNKNOWN
Keywords: mooc,grader,python,python3,education,exgrex,coursera
Platform: UNKNOWN
Classifier: Programming Language :: Python :: 3
Classifier: License :: OSI Approved :: MIT License
Classifier: Operating System :: POSIX :: Linux
Requires-Python: >=3.6
